regression_inference/__init__.py
regression_inference/model.py
regression_inference/services/__init__.py
regression_inference/services/fit_linear.py
regression_inference/services/fit_logit.py
regression_inference/services/fit_logit_multinomial.py
regression_inference/services/fit_logit_multinomial_cuda.py
regression_inference/services/fit_logit_ordinal.py
regression_inference/services/fit_logit_ordinal_cuda.py
regression_inference/services/model_fit.py
regression_inference/services/model_predict.py
regression_inference/services/model_robust_cov.py
regression_inference/services/model_vif.py
regression_inference/utils/__init__.py
regression_inference/utils/cuda_conversion.py
regression_inference/utils/summary.py
regression_inference/utils/table.py
regression_inference/utils/validate.py
regression_inference-1.3.4.dist-info/METADATA
regression_inference-1.3.4.dist-info/WHEEL
regression_inference-1.3.4.dist-info/licenses/LICENSE
regression_inference-1.3.4.dist-info/RECORD
