Metadata-Version: 2.4
Name: regression-inference
Version: 1.3.4
Summary: Regression inference for Python
Project-URL: Homepage, https://github.com/axtaylor/python-ordinary_least_squares
Project-URL: Issues, https://github.com/axtaylor/python-ordinary_least_squares/issues
Author-email: axtaylor <lucasataylor.dev@gmail.com>
License-Expression: MIT
License-File: LICENSE
Classifier: Operating System :: OS Independent
Classifier: Programming Language :: Python :: 3
Requires-Python: >=3.9
Requires-Dist: numpy>=2.0.0
Requires-Dist: scipy>=1.15.0
